useismic/__init__.py
useismic/clients/__init__.py
useismic/clients/old_api_client/__init__.py
useismic/clients/old_api_client/api_client.py
useismic/core/__init__.py
useismic/core/project_manager.py
useismic/processors/__init__.py
useismic/processors/nlloc.py
useismic/settings/__init__.py
useismic/settings/nlloc_settings_template.toml
useismic/settings/services_settings_template.toml
useismic/settings/settings.py
useismic/settings/settings_template.toml
useismic-0.1.6.dist-info/LICENSE
useismic-0.1.6.dist-info/WHEEL
useismic-0.1.6.dist-info/METADATA
useismic-0.1.6.dist-info/RECORD
