Metadata-Version: 2.1
Name: useismic
Version: 0.1.6
Summary: 
License: MIT
Author: jpmercier
Author-email: jpmercier01@gmail.com
Requires-Python: >=3.8,<4.0
Classifier: License :: OSI Approved :: MIT License
Classifier: Programming Language :: Python :: 3
Classifier: Programming Language :: Python :: 3.8
Classifier: Programming Language :: Python :: 3.9
Requires-Dist: dynaconf (>=3.1.4,<4.0.0)
Requires-Dist: uquake (>=0.4.31,<0.5.0)
